git_inquisitor/__init__.py
git_inquisitor/__main__.py
git_inquisitor/chart.py
git_inquisitor/collector.py
git_inquisitor/report.py
git_inquisitor/templates/html.template
git_inquisitor-2024.7.26.dist-info/METADATA
git_inquisitor-2024.7.26.dist-info/WHEEL
git_inquisitor-2024.7.26.dist-info/entry_points.txt
git_inquisitor-2024.7.26.dist-info/RECORD
