Metadata-Version: 2.1
Name: git-inquisitor
Version: 2024.7.26
Summary: Git Inquizitor is an analysis and reporting tool for git repositories.
License: MIT
Author: JP White
Author-email: jpwhite3@gmail.com
Requires-Python: >=3.10,<4.0
Classifier: License :: OSI Approved :: MIT License
Classifier: Programming Language :: Python :: 3
Classifier: Programming Language :: Python :: 3.10
Classifier: Programming Language :: Python :: 3.11
Classifier: Programming Language :: Python :: 3.12
Requires-Dist: GitPython (>=3.1.43,<4.0.0)
Requires-Dist: Jinja2 (>=3.1.3,<4.0.0)
Requires-Dist: click (>=8.1.7,<9.0.0)
Requires-Dist: jinja2-humanize-extension (>=0.4.0,<0.5.0)
Requires-Dist: matplotlib (>=3.8.2,<4.0.0)
Requires-Dist: pytz (>=2024.1,<2025.0)
Requires-Dist: toml (>=0.10.2,<0.11.0)
Requires-Dist: tqdm (>=4.66.1,<5.0.0)
